kenna/__init__.py
kenna/api.py
kenna/authentication.py
kenna/cli/__init__.py
kenna/cli/__main__.py
kenna/cli/command_groups/__init__.py
kenna/cli/command_groups/applications.py
kenna/cli/command_groups/asset_groups.py
kenna/cli/command_groups/assets.py
kenna/cli/command_groups/connectors.py
kenna/cli/command_groups/dashboard_groups.py
kenna/cli/command_groups/fixes.py
kenna/cli/command_groups/integrations.py
kenna/cli/command_groups/roles.py
kenna/cli/command_groups/shortcuts.py
kenna/cli/command_groups/users.py
kenna/cli/command_groups/vulnerabilities.py
kenna/cli/helpers.py
kenna/constants.py
kenna/error.py
kenna/region.py
kenna-0.3.2.dist-info/entry_points.txt
kenna-0.3.2.dist-info/WHEEL
kenna-0.3.2.dist-info/METADATA
kenna-0.3.2.dist-info/RECORD
