Metadata-Version: 2.1
Name: kenna
Version: 0.3.2
Summary: 
Author: Tyler Fisher
Author-email: tylerfisher@tylerfisher.ca
Requires-Python: >=3.7.1,<4
Classifier: Programming Language :: Python :: 3
Classifier: Programming Language :: Python :: 3.8
Classifier: Programming Language :: Python :: 3.9
Requires-Dist: DAWG (>=0.8.0,<0.9.0)
Requires-Dist: altair (>=4.1.0,<5.0.0)
Requires-Dist: antlr4-python3-runtime (>=4.9.2,<5.0.0)
Requires-Dist: certifi (>=2021.5.30,<2022.0.0)
Requires-Dist: click (>=7.0,<8.0)
Requires-Dist: dacite (>=1.6.0,<2.0.0)
Requires-Dist: hodgepodge (>=1.0.3,<2.0.0)
Requires-Dist: pandas (>=1.3.3,<2.0.0)
Requires-Dist: responses (>=0.14.0,<0.15.0)
